CHANGES.txt
LICENSE.txt
MANIFEST.in
README.txt
base.cfg
bootstrap.py
buildout.cfg
setup.py
testing.cfg
worker.cfg
src/s01/__init__.py
src/s01.demo.egg-info/PKG-INFO
src/s01.demo.egg-info/SOURCES.txt
src/s01.demo.egg-info/dependency_links.txt
src/s01.demo.egg-info/namespace_packages.txt
src/s01.demo.egg-info/not-zip-safe
src/s01.demo.egg-info/requires.txt
src/s01.demo.egg-info/top_level.txt
src/s01/demo/__init__.py
src/s01/demo/interfaces.py
src/s01/demo/item.py
src/s01/demo/spiders/__init__.py
src/s01/demo/spiders/pypi.py