Metadata-Version: 1.0
Name: s01.demo
Version: 0.16.2
Summary: Buildout based scrapy spider demo package for s01.worker
Home-page: http://pypi.python.org/pypi/s01.demo
Author: Roger Ineichen, Projekt01 GmbH
Author-email: dev@projekt01.ch
License: ZPL 2.1
Keywords: scrapy s01 p01 mongodb buildout json-rpc zope zope3
Platform: UNKNOWN
Classifier: Development Status :: 4 - Beta
Classifier: Environment :: Web Environment
Classifier: Intended Audience :: Developers
Classifier: License :: OSI Approved :: Zope Public License
Classifier: Programming Language :: Python
Classifier: Natural Language :: English
Classifier: Operating System :: OS Independent
Classifier: Topic :: Internet :: WWW/HTTP
Classifier: Framework :: Zope3
